<?xml version="1.0"?>
<?xml-stylesheet href="../../../../../css/sdo_oxygen.css" type="text/css"?>
<sdo:recordCollection xmlns:dc="http://purl.org/dc/elements/1.1/" xmlns:dcterms="http://purl.org/dc/terms/" xmlns:marcrel="http://www.loc.gov/loc.terms/relators/" xmlns:sdo="http://www.cch.kcl.ac.uk/schenker" xmlns:tei="http://www.tei-c.org/ns/1.0" xmlns:xsi="http://www.w3.org/2001/XMLSchema-instance" xsi:schemaLocation="http://www.cch.kcl.ac.uk/schenker ../../../../../schema/schenker.xsd"><sdo:collectionDesc><sdo:source><!-- MovableType Shelfmark:OC 52/29 : 11-23-08 --><sdo:correspondence shelfmark="TEST-SHELFMARK1" /></sdo:source><tei:handNotes><tei:handNote><!-- Please populate at least one handNote.  Remember to include an xml:id attribute and the scope of the work --></tei:handNote></tei:handNotes><!-- Add additional or remove unnecessary statements of responsiblity as needed below --><tei:respStmt xml:id="IB"><tei:persName>Ian Bent</tei:persName><!-- Add additional or remove unnecessary specific responsibility notes. --><tei:resp>Transcription</tei:resp><tei:resp>XML Encoding</tei:resp><tei:resp>Translation</tei:resp></tei:respStmt><tei:respStmt xml:id="BOT"><tei:name>Automated Script</tei:name><tei:resp>Conversion from MovableType syntax to TEI</tei:resp></tei:respStmt><!-- Add additional change elements below to note major changes to the document --><tei:revisionDesc><tei:change when="2010-01-21" who="#BOT">Template Generated</tei:change></tei:revisionDesc></sdo:collectionDesc><sdo:record ID="r0001"><!-- 
© Universal Edition A.G., Wien.
© Transcription Ian D. Bent 2005.
© Translation Ian D. Bent 2005.
© Commentary, Footnotes, Summary Ian D. Bent 2005.
 --><!-- 
<dcterms:license>email from Aygün Lausch (Universal Edition) to Ian Bent, confirming UE’s ownership of IPR and granting permission to post to pilot website</dcterms:license>
<dcterms:provenance>Schenker, Heinrich (1908-1935) - -Schenker, Jeanette (1935-1938) - -Oster, Ernst (1938-c.1939)—New York Public Library (c.1939-)</dcterms:provenance>
<dcterms:rightsHolder>IPR: Universal Edition, A.G.; Image: New York Public Library, New York; Transcription, Translation, Commentary, Footnotes, and Summary: Ian D. Bent.</dcterms:rightsHolder>
 --><sdo:itemDesc><!-- Date Created: 11/23/1908 01:00:00 AM --><!-- MT Tags: "Hertzka ~ HSchenker","UE ~ H+JSchenker","UE ~ HSchenker" --><dc:title>Typed postcard from Emil Hertzka (UE) to Schenker, dated November 23, 1908</dc:title><dcterms:dateSubmitted>2005-03-14</dcterms:dateSubmitted><dc:description>[Niloff: Instrumentations-Tabelle:]  Is about to go to a larger edition; Hertzka seeks a meeting to discuss.

</dc:description><dc:subject>Hertzka, Emil; UE; Schenker, Heinrich;  Niloff; Instrumentations-Tabelle;  Instrrumentation Table;  large edition; 1st edition</dc:subject><!-- Add the EATS key attribute value to indicate the sender of the letter --><marcrel:correspondent key="EATS_nNNNNNN">  Vienna I, Wipplingerstraße 32</marcrel:correspondent><!-- Add the key attribute to indicate the recipient of the letter --><marcrel:recipient key="EATS_nNNNNNN">  Vienna III, Reisnerstraße 38</marcrel:recipient></sdo:itemDesc><tei:transcription><!-- BODY: --><tei:p><tei:hi rend="bold">Typed postcard from Hertzka (UE) to Schenker, dated November 23, 1908</tei:hi></tei:p><tei:p><tei:hi rend="bold">{<tei:hi rend="italic">recto</tei:hi>}</tei:hi>
Bücherzettel.
An [<tei:hi rend="italic">typed:</tei:hi>] Wohlgeboren [/] Herrn Prof. Dr. Heinrich Schenker,
in  [<tei:hi rend="italic">typed:</tei:hi>] Wien III.
Reisnerstr. 38</tei:p><tei:p>[<tei:hi rend="italic">postmark:</tei:hi>] || 1/1 WIEN 6[?] | 23.XI.08 | <tei:hi rend="bold"> [?] </tei:hi> ||</tei:p><tei:p><tei:hi rend="bold">{<tei:hi rend="italic">verso</tei:hi>}</tei:hi>
Wohlgeboren [/] Herrn Prof. Dr. H. Schenker,
W i e n.</tei:p><tei:p>Sehr geehrter Herr Professor!</tei:p><tei:p>Vielleicht ist es Ihnen doch möglich, uns an einem der nächsten Tage das Vergnügen &lt;sup&gt;&lt;!--add--&gt;Ihres Besuches&lt;/sup&gt; zu machen, nachdem Ihre Instrumentaltabelle,<tei:note xml:id="r0001-fn1">  Niloff: <tei:hi rend="italic">Instrumentations-Tabelle</tei:hi>.</tei:note> welche zunächst in einer kleinen Auflage erschien, nunmehr in einer grossen Auflage<tei:note xml:id="r0001-fn2">  An edition of 2,000 copies was received from the printers on February 9, 1909, and was classified as the official 1st edn.  In a letter to J.G. Cotta of May 26, 1909 (CA 96–98), S gives us further information: “Thus it came about that a pseudonymous work of mine published by UE last Fall had such success that it sold 300 copies within the space of three weeks in Vienna alone, and after only two months a second edition had to be produced.”</tei:note> herauskommen soll und wir diesbezüglich einiges mit Ihnen zu besprechen hätten.</tei:p><tei:p>[<tei:hi rend="italic">printed:</tei:hi>]
[<tei:hi rend="italic">right side:</tei:hi>]
Hochachtungsvoll
"Universal-Edition" A-G.
(Jos. Aibl Verlag, G.m.b.H.)
[<tei:hi rend="italic">signed:</tei:hi>] Hertzka</tei:p><tei:p>[<tei:hi rend="italic">left side:</tei:hi>]
Wien, am [<tei:hi rend="italic">typed:</tei:hi>] 23. 11. 1908
&lt;strike&gt;I. Maximilianstraße 11&lt;/strike&gt;
I. Wipplingerstrasse 32
(Telefon 4921, lokal u. interurban)</tei:p></tei:transcription><tei:translation><!-- EXTENDED BODY: --><tei:p><tei:hi rend="bold">Typed postcard from Hertzka (UE) to Schenker, dated November 23, 1908</tei:hi></tei:p><tei:p><tei:hi rend="bold">{<tei:hi rend="italic">recto</tei:hi>}</tei:hi>
Book Order Form
To: [<tei:hi rend="italic">typed:</tei:hi>] Prof. Heinrich Schenker, Esq.,
Vienna III, 
Reisnerstraße 38</tei:p><tei:p>[<tei:hi rend="italic">postmark:</tei:hi>] || 1/1 VIENNA 6[?] | 23.XI.08 | <tei:hi rend="bold"> [?] </tei:hi> ||</tei:p><tei:p><tei:hi rend="bold">{<tei:hi rend="italic">verso</tei:hi>}</tei:hi>
Prof. H. Schenker, Esq.,
V i e n n a</tei:p><tei:p>Dear Professor,</tei:p><tei:p>Might it be possible for you to do us the pleasure &lt;sup&gt;&lt;!--add--&gt;of paying us a visit&lt;/sup&gt; in the next day or so, since your <tei:hi rend="italic">Instrumentations-Tabelle</tei:hi>,<tei:ptr target="#r0001-fn1"/> which first appeared in a small edition, is now due to be released in a large edition<tei:ptr target="#r0001-fn2"/> and we have one or two things to speak to you about in this connection?</tei:p><tei:p>[<tei:hi rend="italic">printed:</tei:hi>]
[<tei:hi rend="italic">right side:</tei:hi>]
With kind regards, 
Universal Edition &amp; Co.
(Jos. Aibl Verlag &amp; Co.)
[<tei:hi rend="italic">signed:</tei:hi>] Hertzka</tei:p><tei:p>[<tei:hi rend="italic">left side:</tei:hi>]
Vienna, [<tei:hi rend="italic">typed:</tei:hi>] November 23, 1908
&lt;strike&gt;I. Maximilianstraße 11&lt;/strike&gt;
I. Wipplingerstraße 32
(Telephone 4921, local and suburban)</tei:p></tei:translation></sdo:record></sdo:recordCollection>