<?xml version="1.0"?>
<?xml-stylesheet href="../../../../../../css/sdo_oxygen.css" type="text/css"?>
<sdo:recordCollection xmlns:dc="http://purl.org/dc/elements/1.1/" xmlns:dcterms="http://purl.org/dc/terms/" xmlns:marcrel="http://www.loc.gov/loc.terms/relators/" xmlns:sdo="http://www.cch.kcl.ac.uk/schenker" xmlns:tei="http://www.tei-c.org/ns/1.0" xmlns:xsi="http://www.w3.org/2001/XMLSchema-instance" xsi:schemaLocation="http://www.cch.kcl.ac.uk/schenker ../../../../../../schema/schenker.xsd"><sdo:collectionDesc><sdo:source><!-- MovableType Shelfmark:OJ 15/16, [7] : 7-21-12 --><sdo:correspondence shelfmark="TEST-SHELFMARK1" /></sdo:source><tei:handNotes><tei:handNote><!-- Please populate at least one handNote.  Remember to include an xml:id attribute and the scope of the work --></tei:handNote></tei:handNotes><!-- Add additional or remove unnecessary statements of responsiblity as needed below --><tei:respStmt xml:id="IB"><tei:persName>Ian Bent</tei:persName><!-- Add additional or remove unnecessary specific responsibility notes. --><tei:resp>Transcription</tei:resp><tei:resp>XML Encoding</tei:resp><tei:resp>Translation</tei:resp></tei:respStmt><tei:respStmt xml:id="BOT"><tei:name>Automated Script</tei:name><tei:resp>Conversion from MovableType syntax to TEI</tei:resp></tei:respStmt><!-- Add additional change elements below to note major changes to the document --><tei:revisionDesc><tei:change when="2010-01-21" who="#BOT">Template Generated</tei:change></tei:revisionDesc></sdo:collectionDesc><sdo:record ID="r0001"><!-- 
© Under inquiry.
© Transcription Ian Bent and William Drabkin, 2007.
© Translation Ian Bent, 2007.
© Commentary, Footnotes, Summary William Drabkin &amp; Ian Bent 2007
 --><!-- 
<dcterms:license>Permission to publish is being sought.  Any claim to intellectual rights on this document should be addressed to the Schenker Correspondence Project, Faculty of Music, University of Cambridge, at schenkercorrespondence@mus.cam.ac.uk.</dcterms:license>
<dcterms:provenance>Schenker, Heinrich (1912-1935) - -Schenker, Jeanette (1935-c.1942) - -Ratz, Erwin (c.1942-c.1945) - -Jonas, Oswald (c.1945-1978) - -University of California, Riverside (1978 - -)</dcterms:provenance>
<dcterms:rightsHolder>IPR: Heirs of Hans Weisse; Image: University of California, Riverside; Transcription, Translation, Commentary, Footnotes, and Summary: Ian Bent &amp; William Drabkin.</dcterms:rightsHolder>
 --><sdo:itemDesc><!-- Date Created: 07/21/1912 01:00:00 AM --><!-- MT Tags: "Weisse ~ H+JSchenker","Weisse ~ HSchenker" --><dc:title>Handwritten letter from Weisse to Schenker, dated July 21, 1912</dc:title><dcterms:dateSubmitted>2007-10-07</dcterms:dateSubmitted><dc:description>W reports the completion of his string quintet first movement. 

</dc:description><dc:subject>Weisse, Hans;  Schenker, Heinrich;  string quintet;  songform;  sonata form;  rondo form</dc:subject><!-- Add the EATS key attribute value to indicate the sender of the letter --><marcrel:correspondent key="EATS_nNNNNNN">  - -</marcrel:correspondent><!-- Add the key attribute to indicate the recipient of the letter --><marcrel:recipient key="EATS_nNNNNNN">  - -</marcrel:recipient></sdo:itemDesc><tei:transcription><!-- BODY: --><tei:p><tei:hi rend="bold">Handwritten letter from Weisse to Schenker, dated July 21, 1912</tei:hi></tei:p><tei:p>Geliebter Meister!</tei:p><tei:p>Mit grosser Freude schreibe ich Ihnen heute, weil ich Ihnen zugleich mit dem Dank für Ihre letzten lieben Zeilen,<tei:note xml:id="r0001-fn1">  The communication that this acknowledges is not known to survive.  </tei:note> die ich durch &lt;strike&gt;durch&lt;/strike&gt; ein Missverständnis verspätet erhielt – die Mitteilung machen kann, dass der erste Satz meines Streichquintetts<tei:note xml:id="r0001-fn2">  See OJ 15/16, [6], July 7, 1912, for the first mention of this composition, and subsequent letters and diary entries by S.  </tei:note> vollständig fertig komponiert und instrumentiert vor mir liegt!  Es ist eine grosse Freude für mich, besonders weil dieser <tei:hi rend="bold">{2}</tei:hi> erste Versuch ins Reich grosser Formen überzugehen wie mir scheint nicht ganz misslungen ist.  Gewiss wird manches auszusetzen sein aber im grossen und ganzen bin ich der Form doch so ziemlich gerecht worden und bin besonders mit der Synthese zufrieden!  Wie die Meister auf dem Gebiete spucken habe ich Ihnen zu meiner eignen (hoffentlich auch zu der Ihren) Zufriedenheit abgeguckt!  Die Erfindung von Brahmsweisen stark abweichend[,] hoffentlich auch zu Ihrer <tei:hi rend="bold">{3}</tei:hi> Freude!</tei:p><tei:p>Soweit ich mich überhaupt mit dem folgenden beschäftige, denke ich den langsamen Satz in einfacher Liedform auszudrücken, das Scherzo in Sonatenform, und den letzten Satz in Rondoform.  Wäre da</tei:p><tei:p>a – b – a , – c , – a&lt;sub&gt;2&lt;/sub&gt; – d , a&lt;sub&gt;3&lt;/sub&gt; – b –  a&lt;sub&gt;4&lt;/sub&gt; möglich?</tei:p><tei:p>Die Coda habe ich ganz nach meinem innersten Gefühl gemacht!</tei:p><tei:p>Verzeihen Sie, wenn ich heute schon schliesse – aber die Zeit eilt und ich habe noch zu marschieren!</tei:p><tei:p><tei:hi rend="bold">{4} </tei:hi>Seien Sie liebster Doktor herzlichst gegrüsst und lassen Sie bald etwas von sich hören!</tei:p><tei:p>Ihr getreuer 
[<tei:hi rend="italic">signed:</tei:hi>] Hans.
21. Juli 1912</tei:p></tei:transcription><tei:translation><!-- EXTENDED BODY: --><tei:p><tei:hi rend="bold">Handwritten letter from Weisse to Schenker, dated July 21, 1912</tei:hi></tei:p><tei:p>Beloved master,</tei:p><tei:p>I write to you today with great joy, because while thanking you for your latest dear missive<tei:ptr target="#r0001-fn1"/>—which I received belatedly as a result of a misunderstanding—I can at the same time impart to you the news that I have the first movement of my string quintet<tei:ptr target="#r0001-fn2"/> before me, its composition and instrumentation fully completed!  It is a great delight to me, especially because this <tei:hi rend="bold">{2}</tei:hi> first attempt to enter the realm of the larger forms has not, as it seems to me, completely misfired.  For sure, there is still a great deal to settle, but on the whole I have really pretty well done justice to the form and am especially content with the synthesis!  I have learned to my own satisfaction (and I hope to yours, too) how the masters tackle this sphere.  Its invention setting out strongly from Brahms’s manner, I hope [it will afford you] <tei:hi rend="bold">{3}</tei:hi> pleasure, too!</tei:p><tei:p>Insofar as I am at work at all on what comes next, I am thinking of the slow movement in terms of simple songform, the scherzo as sonata form, and the final movement as rondo form.  For that, would</tei:p><tei:p>a – b – a , – c , – a&lt;sub&gt;2&lt;/sub&gt; – d , a&lt;sub&gt;3&lt;/sub&gt; – b –  a&lt;sub&gt;4&lt;/sub&gt;  be possible?</tei:p><tei:p>I have fashioned the coda entirely according to my innermost feelings!</tei:p><tei:p>Forgive me if I close at this point for today—but time is short and I still have to get my skates on!</tei:p><tei:p><tei:hi rend="bold">{4}</tei:hi> Please accept my most cordial greetings, dearest doctor, and let me hear from you soon!</tei:p><tei:p>Yours faithfuly,
[<tei:hi rend="italic">signed:</tei:hi>] Hans
July 21, 1912</tei:p></tei:translation></sdo:record></sdo:recordCollection>