<?xml version="1.0"?>
<?xml-stylesheet href="../../../../../../css/sdo_oxygen.css" type="text/css"?>
<sdo:recordCollection xmlns:dc="http://purl.org/dc/elements/1.1/" xmlns:dcterms="http://purl.org/dc/terms/" xmlns:marcrel="http://www.loc.gov/loc.terms/relators/" xmlns:sdo="http://www.cch.kcl.ac.uk/schenker" xmlns:tei="http://www.tei-c.org/ns/1.0" xmlns:xsi="http://www.w3.org/2001/XMLSchema-instance" xsi:schemaLocation="http://www.cch.kcl.ac.uk/schenker ../../../../../../schema/schenker.xsd"><sdo:collectionDesc><sdo:source><!-- MovableType Shelfmark:OJ 11/54, [17] : 9-6-27 --><sdo:correspondence shelfmark="TEST-SHELFMARK1" /></sdo:source><tei:handNotes><tei:handNote><!-- Please populate at least one handNote.  Remember to include an xml:id attribute and the scope of the work --></tei:handNote></tei:handNotes><!-- Add additional or remove unnecessary statements of responsiblity as needed below --><tei:respStmt xml:id="IB"><tei:persName>Ian Bent</tei:persName><!-- Add additional or remove unnecessary specific responsibility notes. --><tei:resp>Transcription</tei:resp><tei:resp>XML Encoding</tei:resp><tei:resp>Translation</tei:resp></tei:respStmt><tei:respStmt xml:id="BOT"><tei:name>Automated Script</tei:name><tei:resp>Conversion from MovableType syntax to TEI</tei:resp></tei:respStmt><!-- Add additional change elements below to note major changes to the document --><tei:revisionDesc><tei:change when="2010-01-21" who="#BOT">Template Generated</tei:change></tei:revisionDesc></sdo:collectionDesc><sdo:record ID="r0001"><!-- 
© Heirs of Anthony van Hoboken, published here with kind permission.  
© Transcription John Rothgeb, 2008.
© Translation John Rothgeb, 2008.
© Commentary, Footnotes, Summary John Rothgeb 2008
 --><!-- 
<dcterms:license>Permission to publish granted by the heirs of Anthony van Hoboken February 3, 2007.  Any claim to intellectual rights on this document should be addressed to the Schenker Correspondence Project, Faculty of Music, University of Cambridge, at schenkercorrespondence@mus.cam.ac.uk.</dcterms:license>
<dcterms:provenance>Schenker, Heinrich (1927-1935) - -Schenker, Jeanette (1935-c.1942) - -Ratz, Erwin (c.1942-c.1945) - -Jonas, Oswald (c.1945-1978) - -University of California, Riverside (1978 - -)</dcterms:provenance>
<dcterms:rightsHolder>IPR: Heirs of Anthony van Hoboken; Image: University of California, Riverside; Transcription, Translation, Commentary, Footnotes, and Summary: John Rothgeb.</dcterms:rightsHolder>
 --><sdo:itemDesc><!-- Date Created: 09/06/1927 01:00:00 AM --><!-- MT Tags: "Hoboken ~ H+JSchenker","Hoboken ~ HSchenker" --><dc:title>Handwritten letter from Hoboken to Schenker, dated September 6, 1927</dc:title><dcterms:dateSubmitted>2008-06-05</dcterms:dateSubmitted><dc:description>Van Hoboken reports from Drei-Masken Verlag that Vrieslander's text for the Meisterwerk prospectus is overlength, and seeks Schenker's opinion.  

</dc:description><dc:subject>Hoboken, Anthony van;  Schenker, Heinrich;  Drei-Masken-Verlag;  Yearbook;  Meisterwerk in der Musik;  Masterwork in Music;  Vrieslander, Otto</dc:subject><!-- Add the EATS key attribute value to indicate the sender of the letter --><marcrel:correspondent key="EATS_nNNNNNN">  Hotel Frankfurter Hof, Frankfurt a/M</marcrel:correspondent><!-- Add the key attribute to indicate the recipient of the letter --><marcrel:recipient key="EATS_nNNNNNN">  - -</marcrel:recipient></sdo:itemDesc><tei:transcription><!-- BODY: --><tei:p><tei:hi rend="bold">Handwritten letter from van Hoboken to Schenker dated September 6, 1927</tei:hi></tei:p><tei:p>[<tei:hi rend="italic">printed letterhead:</tei:hi>]
Hotel Frankfurter Hof
Frankfurt a/M.
[<tei:hi rend="italic">detailed printed contact information next to lithograph of hotel</tei:hi>]
den <tei:hi rend="italic">6. IX.</tei:hi> 19<tei:hi rend="italic">27</tei:hi></tei:p><tei:p>[<tei:hi rend="italic">handwritten:</tei:hi>]
Lieber Herr Professor,<tei:note xml:id="r0001-fn1">  Receipt recorded in Schenker's diary, &lt;a href="../../../../../diary/oj<tei:hi rend="italic">39</tei:hi>p<tei:hi rend="italic">3112</tei:hi>91327.html"&gt;OJ 3/9, p. 3112&lt;/a&gt;, September 13, 1927.  </tei:note></tei:p><tei:p>Soeben komme ich in Frankfurt an und finde folgende Nachricht vor:</tei:p><tei:p>Der Drei-Masken-Verlag berichtet, dass &lt;strike&gt;Sie&lt;/strike&gt; sie mit der Drucklegung des Prospektes für Ihr Jahrbuch<tei:note xml:id="r0001-fn2">  <tei:hi rend="italic">Yearbook</tei:hi>:  Schenker's <tei:hi rend="italic">Das Meisterwerk in der Musik</tei:hi>.  </tei:note> angefangen hat, dass aber der Text von Vrieslander<tei:note xml:id="r0001-fn3">  Click on <ref cRef="vrieslander_otto">Otto Vrieslander</ref>.  </tei:note> weit über den Rahmen eines gewöhnlichen Prospektes hinausgehe, und dass, falls er ungekürzt abgedruckt werden soll, ich die Kosten davon übernehmen soll. – Ich bin hier nicht im Bilde und weiss nicht, was seinerzeit wegen eines Prospektes verabredet wurde.  Ich möchte Sie daher fragen, ob Sie den Vrieslanderschen Text kennen, und ob Sie der Meinung sind, dass derselbe nicht gekürzt werden kann.  Sodann will ich gerne die Kosten für die Drucklegung auch noch<tei:note xml:id="r0001-fn4">  That is, in addition to the cost of printing the <tei:hi rend="italic">Yearbook</tei:hi> itself.</tei:note> auf mich nehmen.</tei:p><tei:p>Ich bitte Sie, mich entschuldigen zu wollen dass ich für heute nichts weiter schreibe und bin</tei:p><tei:p>Ihr ganz ergebener
[<tei:hi rend="italic">signed:</tei:hi>] AvHoboken</tei:p></tei:transcription><tei:translation><!-- EXTENDED BODY: --><tei:p><tei:hi rend="bold">Handwritten letter from van Hoboken to Schenker dated September 6, 1927</tei:hi></tei:p><tei:p>[<tei:hi rend="italic">printed letterhead:</tei:hi>]
Hotel Frankfurter Hof
Frankfurt a/M.
[<tei:hi rend="italic">detailed printed contact information next to lithograph of hotel</tei:hi>]
<tei:hi rend="italic">September 6, </tei:hi> 19<tei:hi rend="italic">27</tei:hi></tei:p><tei:p>[<tei:hi rend="italic">handwritten:</tei:hi>]
Dear Professor [Schenker],<tei:ptr target="#r0001-fn1"/></tei:p><tei:p>Immediately on arrival in Frankfurt I find the following information:</tei:p><tei:p>Drei-Masken Verlag reports that they have begun printing off the prospectus for your <tei:hi rend="italic">Yearbook</tei:hi>,<tei:ptr target="#r0001-fn2"/> but that the text by Vrieslander<tei:ptr target="#r0001-fn3"/> far exceeds the boundaries of a usual prospectus, and that, if it is to be printed without abridgment, I am to absorb the cost. —This is news to me, and I don’t know what was agreed upon at the time regarding a prospectus.  Thus I would like to ask whether you know the Vrieslander text and whether in your opinion it could not be shortened.  Then I will gladly assume the costs for printing [it] as well.<tei:ptr target="#r0001-fn4"/></tei:p><tei:p>I ask your pardon that I write nothing more for today, and I am</tei:p><tei:p>Yours sincerely,
[<tei:hi rend="italic">signed:</tei:hi>] A. v. Hoboken</tei:p></tei:translation></sdo:record></sdo:recordCollection>